r_freeze/__init__.py
r_freeze/cli.py
r_freeze/r_freeze.py
r_freeze-0.1.1.dist-info/METADATA
r_freeze-0.1.1.dist-info/RECORD
r_freeze-0.1.1.dist-info/WHEEL
r_freeze-0.1.1.dist-info/entry_points.txt
r_freeze-0.1.1.dist-info/top_level.txt
