Metadata-Version: 2.1
Name: r-freeze
Version: 0.1.1
Summary: Pipreqs for R
Home-page: https://github.com/chinmayshah99/r_freeze
Author: Chinmay Shah
Author-email: chinmayshah3899@gmail.com
License: MIT license
Keywords: r_freeze
Platform: UNKNOWN
Classifier: Development Status :: 2 - Pre-Alpha
Classifier: Intended Audience :: Developers
Classifier: License :: OSI Approved :: MIT License
Classifier: Natural Language :: English
Classifier: Programming Language :: Python :: 3
Classifier: Programming Language :: Python :: 3.5
Classifier: Programming Language :: Python :: 3.6
Classifier: Programming Language :: Python :: 3.7
Classifier: Programming Language :: Python :: 3.8
Requires-Python: >=3.5
